exprec/__init__.py
exprec/compare_creation.py
exprec/constants.py
exprec/dashboard.py
exprec/experiment_creation.py
exprec/html_utils.py
exprec/index.html
exprec/runner.py
exprec/table_creation.py
exprec/test.py
exprec/utils.py
exprec/css/mystyle.css
exprec/js/main.js
exprec/static/favicon.ico
exprec-0.1.1.data/scripts/exprec
exprec-0.1.1.dist-info/LICENSE
exprec-0.1.1.dist-info/METADATA
exprec-0.1.1.dist-info/WHEEL
exprec-0.1.1.dist-info/top_level.txt
exprec-0.1.1.dist-info/RECORD
