Metadata-Version: 2.1
Name: exprec
Version: 0.1.1
Summary: Exprec records your experiments so you can compare different runs and easily reproduce results.
Home-page: https://github.com/martno/exprec/
Author: Martin Nordstrom
Author-email: martin.nordstrom87@gmail.com
License: MIT license
Platform: UNKNOWN
Classifier: Programming Language :: Python
Classifier: Programming Language :: Python :: 3
Classifier: Programming Language :: Python :: 3.4
Classifier: Programming Language :: Python :: 3.5
Classifier: Programming Language :: Python :: 3.6
Classifier: License :: OSI Approved :: MIT License
Classifier: Operating System :: OS Independent
Requires-Dist: Flask (>=0.12.2)
Requires-Dist: attrs (>=17.4.0)
Requires-Dist: bokeh (==0.12.15)
Requires-Dist: humanize (>=0.5.1)
Requires-Dist: pandas (>=0.22.0)
Requires-Dist: GitPython (>=2.1.10)
Requires-Dist: colorhash (>=1.0.2)
Requires-Dist: markdown (>=2.6.11)
Requires-Dist: psutil (>=5.4.6)
Requires-Dist: Pillow (>=5.1.0)
Requires-Dist: Jinja2 (>=2.10)
